supertab/__init__.py
supertab/db.py
supertab/models.py
supertab/tab_manager.py
supertab-1.0.1.dist-info/METADATA
supertab-1.0.1.dist-info/WHEEL
supertab-1.0.1.dist-info/top_level.txt
supertab-1.0.1.dist-info/RECORD
