Metadata-Version: 2.1
Name: supertab
Version: 1.0.1
Summary: Reusable library for tab management using SQLAlchemy
Home-page: UNKNOWN
Author: Ascendeum
Author-email: engineering@ascendeum.com
License: UNKNOWN
Platform: UNKNOWN
Requires-Python: >=3.6
Requires-Dist: SQLAlchemy (>=1.3)
Requires-Dist: PyMySQL (>=1.0)
